sopel_github/__init__.py
sopel_github/formatting.py
sopel_github/plugin.py
sopel_github/webhook.py
sopel_github-0.5.0.dist-info/COPYING
sopel_github-0.5.0.dist-info/METADATA
sopel_github-0.5.0.dist-info/WHEEL
sopel_github-0.5.0.dist-info/entry_points.txt
sopel_github-0.5.0.dist-info/top_level.txt
sopel_github-0.5.0.dist-info/RECORD
