Metadata-Version: 2.1
Name: sopel-github
Version: 0.5.0
Summary: GitHub plugin for Sopel
Author-email: Max Gurela <maxpowa@outlook.com>
Maintainer-email: dgw <dgw@technobabbl.es>
License: EFL-2.0
Project-URL: Homepage, https://github.com/sopel-irc/sopel-github
Project-URL: Bug Tracker, https://github.com/sopel-irc/sopel-github/issues
Keywords: sopel,plugin,bot,irc
Platform: Linux x86, x86-64
Classifier: Intended Audience :: Developers
Classifier: Intended Audience :: System Administrators
Classifier: License :: Eiffel Forum License (EFL)
Classifier: License :: OSI Approved :: Eiffel Forum License
Classifier: Programming Language :: Python :: 3 :: Only
Classifier: Topic :: Communications :: Chat :: Internet Relay Chat
Requires-Python: <4,>=3.8
License-File: COPYING
Requires-Dist: sopel>=8
Requires-Dist: bottle~=0.12.0
Provides-Extra: emojize
Requires-Dist: emoji<3,>=2.0; extra == "emojize"
